vcf2fhir/__init__.py
vcf2fhir/common.py
vcf2fhir/converter.py
vcf2fhir/fhir_helper.py
vcf2fhir/gene_ref_seq.py
vcf2fhir/json_generator.py
vcf2fhir/test/__init__.py
vcf2fhir/test/test_integration.py
vcf2fhir/test/test_unit.py
vcf2fhir-0.1.1.dist-info/LICENSE
vcf2fhir-0.1.1.dist-info/METADATA
vcf2fhir-0.1.1.dist-info/WHEEL
vcf2fhir-0.1.1.dist-info/top_level.txt
vcf2fhir-0.1.1.dist-info/RECORD
