Metadata-Version: 2.1
Name: vcf2fhir
Version: 0.1.1
Summary: Convert .vcf files to HL7 FHIR standard
Home-page: https://github.com/elimuinformatics/vcf2fhir
Author: ""
Author-email: info@elimu.io
License: Apache Software License
Classifier: Programming Language :: Python :: 3
Classifier: Operating System :: OS Independent
Classifier: License :: OSI Approved :: Apache Software License
License-File: LICENSE
Requires-Dist: Cython (>=0.29.21)
Requires-Dist: fhirclient (==3.2.0)
Requires-Dist: pysam
Requires-Dist: pandas
Requires-Dist: pytz (>=2019.3)
Requires-Dist: PyVCF3 (>=1.0.3)
Requires-Dist: pyranges (>=0.0.96)
